[{"__type__":"cc.AnimationClip","_name":"wavingCatAnim","_duration":0.6833333333333333,"wrapMode":2,"curveData":{"comps":{"cc.Sprite":{"spriteFrame":[{"frame":0,"value":{"__uuid__":"16a0aa49-ab11-4178-bebc-5b5d87c7a6b7"}},{"frame":0.08333333333333333,"value":{"__uuid__":"3bbbff36-69d3-4c08-99df-452a96302dbc"}},{"frame":0.16666666666666666,"value":{"__uuid__":"c0b05046-f4ac-4748-af54-73ea1024939d"}},{"frame":0.25,"value":{"__uuid__":"ad63d5ba-28bb-4f76-aeb6-2c756a236730"}},{"frame":0.3333333333333333,"value":{"__uuid__":"d1410aff-c8f3-4e53-b6e6-72f7f8182583"}},{"frame":0.4166666666666667,"value":{"__uuid__":"41ae6584-f79c-4b56-aeba-bc8b023e397b"}},{"frame":0.5,"value":{"__uuid__":"8b4bb6b4-db13-4686-8779-f007ae1b5a49"}},{"frame":0.5833333333333334,"value":{"__uuid__":"8b4bb6b4-db13-4686-8779-f007ae1b5a49"}},{"frame":0.6666666666666666,"value":{"__uuid__":"16a0aa49-ab11-4178-bebc-5b5d87c7a6b7"}}]}}}},{"__type__":"cc.SpriteFrame","content":{"name":"winken-01","texture":"9488d88e-e592-453c-8d98-9a888e09d772","rect":[0,101,101,100],"offset":[0,0],"originalSize":[101,100]}},{"__type__":"cc.SpriteFrame","content":{"name":"winken-02","texture":"9488d88e-e592-453c-8d98-9a888e09d772","rect":[0,303,100,100],"offset":[0,0],"originalSize":[100,100]}},{"__type__":"cc.SpriteFrame","content":{"name":"winken-03","texture":"9488d88e-e592-453c-8d98-9a888e09d772","rect":[0,404,100,100],"offset":[0,0],"originalSize":[100,100]}},{"__type__":"cc.SpriteFrame","content":{"name":"winken-04","texture":"9488d88e-e592-453c-8d98-9a888e09d772","rect":[0,303,100,100],"offset":[0,0],"originalSize":[100,100]}},{"__type__":"cc.SpriteFrame","content":{"name":"winken-06","texture":"9488d88e-e592-453c-8d98-9a888e09d772","rect":[0,202,100,100],"offset":[0,0],"originalSize":[100,100]}},{"__type__":"cc.SpriteFrame","content":{"name":"winken-07","texture":"9488d88e-e592-453c-8d98-9a888e09d772","rect":[0,0,101,100],"offset":[0,0],"originalSize":[101,100]}},{"__type__":"cc.SpriteFrame","content":{"name":"winken-08","texture":"9488d88e-e592-453c-8d98-9a888e09d772","rect":[0,202,100,100],"offset":[0,0],"originalSize":[100,100]}},[{"__type__":"cc.Prefab","_name":"EnemyNinja","data":{"__id__":1}},{"__type__":"cc.Node","_name":"EnemyNinja","_children":[{"__id__":2},{"__id__":3}],"_scaleX":0.5,"_scaleY":0.5,"_position":{"__type__":"cc.Vec2","x":414,"y":-154},"_components":[{"__type__":"930928NwAhILqGlYjjAFt//","node":{"__id__":1},"attackRadius":50,"xSpeed":150,"ySpeed":100,"animation":{"__id__":4},"strength":5,"health":50,"enemyType":"enemyNinja"}]},{"__type__":"cc.Node","_name":"shadow","_opacity":127,"_parent":{"__id__":1},"_contentSize":{"__type__":"cc.Size","width":190,"height":80},"_scaleX":0.7,"_scaleY":0.7,"_position":{"__type__":"cc.Vec2","x":-9.1,"y":-102},"_components":[{"__type__":"cc.Sprite","node":{"__id__":2},"_spriteFrame":{"__uuid__":"cfa7098a-3185-4737-b253-6d9652b560d7"}}]},{"__type__":"cc.Node","_name":"EnemyNinjaAnimation","_parent":{"__id__":1},"_contentSize":{"__type__":"cc.Size","width":193,"height":202},"_components":[{"__type__":"cc.Sprite","node":{"__id__":3},"_spriteFrame":{"__uuid__":"a04d73bc-fb13-4843-906d-bc1f2daf82c0"}},{"__id__":4},{"__type__":"91258aRkStMNKIdC18bjsS+","node":{"__id__":3},"stepAudio":{"__uuid__":"fa2f10d3-b769-47a4-9f0f-8396f893df7f"},"punchAudio":{"__uuid__":"35f7b7de-81a3-4f88-a100-890666319786"}}]},{"__type__":"cc.Animation","node":{"__id__":3},"_defaultClip":{"__uuid__":"f678c5ec-aa28-4211-a36a-f2953721d959"},"_clips":[{"__uuid__":"6d82e49a-6b55-46bb-b24f-736169cf90a0"},{"__uuid__":"f678c5ec-aa28-4211-a36a-f2953721d959"},{"__uuid__":"87c2b0dd-036b-4636-9c7b-459f53bf8d23"},{"__uuid__":"4a70ad42-583f-4fea-996f-922caaf66af2"},{"__uuid__":"5434c3bd-cc7b-4c26-9ede-3738307bb361"}]}],{"__type__":"cc.SpriteFrame","content":{"name":"ninja-0","texture":"c0e9c5a5-2b0d-4d90-95ef-8be2cbff2a1c","rect":[0,203,193,202],"offset":[0,0],"originalSize":[250,250]}},{"__type__":"cc.AnimationClip","_name":"enemyRunLeftAnim_enemyNinja","_duration":0.35,"wrapMode":2,"curveData":{"props":{"scaleX":[{"frame":0,"value":-1}]},"comps":{"cc.Sprite":{"spriteFrame":[{"frame":0,"value":{"__uuid__":"a04d73bc-fb13-4843-906d-bc1f2daf82c0"}},{"frame":0.08333333333333333,"value":{"__uuid__":"3f6f6e44-9f00-44dc-add6-ccbe5f51fb7b"}},{"frame":0.16666666666666666,"value":{"__uuid__":"493561d6-d7e8-4ec5-98ce-aef4d2838b49"}},{"frame":0.25,"value":{"__uuid__":"42745e89-0f39-4932-bfd5-099861e31712"}},{"frame":0.3333333333333333,"value":{"__uuid__":"a04d73bc-fb13-4843-906d-bc1f2daf82c0"}}]}}}},{"__type__":"cc.SpriteFrame","content":{"name":"ninja-1","texture":"c0e9c5a5-2b0d-4d90-95ef-8be2cbff2a1c","rect":[196,0,171,207],"offset":[0,0],"originalSize":[250,250]}},{"__type__":"cc.SpriteFrame","content":{"name":"ninja-2","texture":"c0e9c5a5-2b0d-4d90-95ef-8be2cbff2a1c","rect":[0,616,184,200],"offset":[0,0],"originalSize":[250,250]}},{"__type__":"cc.SpriteFrame","content":{"name":"ninja-3","texture":"c0e9c5a5-2b0d-4d90-95ef-8be2cbff2a1c","rect":[0,0,195,202],"offset":[0,0],"originalSize":[250,250]}},{"__type__":"cc.AnimationClip","_name":"enemyRunRightAnim_enemyNinja","_duration":0.35,"wrapMode":2,"curveData":{"props":{"scaleX":[{"frame":0,"value":1}]},"comps":{"cc.Sprite":{"spriteFrame":[{"frame":0,"value":{"__uuid__":"a04d73bc-fb13-4843-906d-bc1f2daf82c0"}},{"frame":0.08333333333333333,"value":{"__uuid__":"3f6f6e44-9f00-44dc-add6-ccbe5f51fb7b"}},{"frame":0.16666666666666666,"value":{"__uuid__":"493561d6-d7e8-4ec5-98ce-aef4d2838b49"}},{"frame":0.25,"value":{"__uuid__":"42745e89-0f39-4932-bfd5-099861e31712"}},{"frame":0.3333333333333333,"value":{"__uuid__":"a04d73bc-fb13-4843-906d-bc1f2daf82c0"}}]}}}},{"__type__":"cc.AnimationClip","_name":"enemyPunchAnim_enemyNinja","_duration":0.4,"curveData":{"comps":{"cc.Sprite":{"spriteFrame":[{"frame":0,"value":{"__uuid__":"9da967f1-cf7e-41b6-879a-7a6b93c99f42"}},{"frame":0.08333333333333333,"value":{"__uuid__":"74f6fc78-9830-40cb-aa32-3473c21a9533"}},{"frame":0.26666666666666666,"value":{"__uuid__":"777d765a-47e8-408f-95cd-8083c537a89c"}},{"frame":0.38333333333333336,"value":{"__uuid__":"9da967f1-cf7e-41b6-879a-7a6b93c99f42"}}]}}},"events":[{"frame":0.2833333333333333,"func":"playPunchSound","params":[]}]},{"__type__":"cc.SpriteFrame","content":{"name":"ninja-4","texture":"c0e9c5a5-2b0d-4d90-95ef-8be2cbff2a1c","rect":[185,616,181,209],"offset":[0,0],"originalSize":[250,250]}},{"__type__":"cc.SpriteFrame","content":{"name":"ninja-5","texture":"c0e9c5a5-2b0d-4d90-95ef-8be2cbff2a1c","rect":[368,0,161,243],"offset":[0,0],"originalSize":[250,250]}},{"__type__":"cc.SpriteFrame","content":{"name":"ninja-6","texture":"c0e9c5a5-2b0d-4d90-95ef-8be2cbff2a1c","rect":[0,406,189,209],"offset":[0,0],"originalSize":[250,250]}},{"__type__":"cc.AnimationClip","_name":"enemyDieAnim_enemyNinja","_duration":0.4166666666666667,"curveData":{"comps":{"cc.Sprite":{"spriteFrame":[{"frame":0,"value":{"__uuid__":"c71df3a5-f658-4b8b-95ed-1a3c7d684f09"}},{"frame":0.08333333333333333,"value":{"__uuid__":"44a31a47-3316-45a4-9625-b7019b4cbd85"}},{"frame":0.16666666666666666,"value":{"__uuid__":"40d84f06-98e0-48e6-a268-eb5f43f1e9a7"}},{"frame":0.3333333333333333,"value":{"__uuid__":"40d84f06-98e0-48e6-a268-eb5f43f1e9a7"}}]}},"props":{"opacity":[{"frame":0.16666666666666666,"value":255},{"frame":0.4166666666666667,"value":0}]}}},{"__type__":"cc.SpriteFrame","content":{"name":"ninja-8","texture":"c0e9c5a5-2b0d-4d90-95ef-8be2cbff2a1c","rect":[0,835,146,187],"offset":[0,0],"originalSize":[250,250]}},{"__type__":"cc.SpriteFrame","content":{"name":"ninja-9","texture":"c0e9c5a5-2b0d-4d90-95ef-8be2cbff2a1c","rect":[147,835,133,135],"offset":[0,0],"originalSize":[250,250]}},{"__type__":"cc.SpriteFrame","content":{"name":"ninja-10","texture":"c0e9c5a5-2b0d-4d90-95ef-8be2cbff2a1c","rect":[194,208,96,97],"offset":[0,0],"originalSize":[250,250]}},{"__type__":"cc.AnimationClip","_name":"enemyTumbleAnim_enemyNinja","_duration":0.7666666666666667,"wrapMode":2,"curveData":{"comps":{"cc.Sprite":{"spriteFrame":[{"frame":0,"value":{"__uuid__":"a4f7b57d-18fd-4efd-8e8e-6cbda12fc536"}},{"frame":0.23333333333333334,"value":{"__uuid__":"9f5b2453-991f-4d0f-8fda-f4d21715b176"}},{"frame":0.5,"value":{"__uuid__":"82c9785d-6762-4eaf-8fa5-fc08e8f13b9d"}},{"frame":0.75,"value":{"__uuid__":"a4f7b57d-18fd-4efd-8e8e-6cbda12fc536"}}]}}}},{"__type__":"cc.SpriteFrame","content":{"name":"ninja-11","texture":"c0e9c5a5-2b0d-4d90-95ef-8be2cbff2a1c","rect":[190,406,181,209],"offset":[0,0],"originalSize":[250,250]}},{"__type__":"cc.SpriteFrame","content":{"name":"ninja-12","texture":"c0e9c5a5-2b0d-4d90-95ef-8be2cbff2a1c","rect":[367,616,161,218],"offset":[0,0],"originalSize":[250,250]}},{"__type__":"cc.SpriteFrame","content":{"name":"ninja-13","texture":"c0e9c5a5-2b0d-4d90-95ef-8be2cbff2a1c","rect":[372,244,158,233],"offset":[0,0],"originalSize":[250,250]}}]